README.rst
setup.py
oct/__init__.py
oct.egg-info/PKG-INFO
oct.egg-info/SOURCES.txt
oct.egg-info/dependency_links.txt
oct.egg-info/entry_points.txt
oct.egg-info/requires.txt
oct.egg-info/top_level.txt
oct/core/__init__.py
oct/core/devices.py
oct/core/exceptions.py
oct/core/hq.py
oct/core/turrets_manager.py
oct/results/__init__.py
oct/results/graphs.py
oct/results/models.py
oct/results/output.py
oct/results/report.py
oct/results/stats_handler.py
oct/results/writer.py
oct/tools/__init__.py
oct/tools/from_armory.py
oct/tools/rebuild_results.py
oct/tools/results_to_csv.py
oct/utilities/__init__.py
oct/utilities/commands.py
oct/utilities/configuration.py
oct/utilities/newproject.py
oct/utilities/pack.py
oct/utilities/run.py
oct/utilities/run_device.py
oct/utilities/templates/configuration/config.json
oct/utilities/templates/css/bootstrap.min.css
oct/utilities/templates/css/dataTables.bootstrap.min.css
oct/utilities/templates/css/style.css
oct/utilities/templates/fonts/glyphicons-halflings-regular.eot
oct/utilities/templates/fonts/glyphicons-halflings-regular.svg
oct/utilities/templates/fonts/glyphicons-halflings-regular.ttf
oct/utilities/templates/fonts/glyphicons-halflings-regular.woff
oct/utilities/templates/fonts/glyphicons-halflings-regular.woff2
oct/utilities/templates/html/report.html
oct/utilities/templates/javascript/bootstrap.min.js
oct/utilities/templates/javascript/dataTables.bootstrap.min.js
oct/utilities/templates/javascript/jquery-2.2.3.min.js
oct/utilities/templates/javascript/jquery.dataTables.min.js
oct/utilities/templates/javascript/oct.js
oct/utilities/templates/javascript/pygal-tooltip.min.js
oct/utilities/templates/scripts/setup.j2
oct/utilities/templates/scripts/v_user.j2