Metadata-Version: 1.1
Name: oct
Version: 0.4.8
Summary: A library for performances testing, give you the tools for load testing anything with any language
Home-page: https://github.com/TheGhouls/oct
Author: TheGhouls
Author-email: manu.valette@gmail.com
License: UNKNOWN
Download-URL: https://github.com/TheGhouls/oct/archive/master.zip
Keywords: testing,perfs,performances,web,load,zeromq
Platform: UNKNOWN
Classifier: Development Status :: 4 - Beta
Classifier: Environment :: Console
Classifier: Intended Audience :: Developers
Classifier: Intended Audience :: System Administrators
Classifier: License :: OSI Approved :: MIT License
Classifier: Programming Language :: Python :: 2.7
Classifier: Programming Language :: Python :: 3.4
Classifier: Programming Language :: Python :: 3.5
